dfb/__init__.py
dfb/backup.py
dfb/cli.py
dfb/cliutils.py
dfb/configuration.py
dfb/dstdb.py
dfb/listing.py
dfb/prune.py
dfb/rclonecli.py
dfb/rclonerc.py
dfb/restore.py
dfb/threadmapper.py
dfb/timestamps.py
dfb/utils.py
dfblink/__init__.py
dfblink/cli.py
dfblink/link.py
dfbmount/__init__.py
dfbmount/fuse.py
dfbmount/mount.py
dfb-20250711.0b0.dist-info/METADATA
dfb-20250711.0b0.dist-info/WHEEL
dfb-20250711.0b0.dist-info/entry_points.txt
dfb-20250711.0b0.dist-info/top_level.txt
dfb-20250711.0b0.dist-info/RECORD
