Metadata-Version: 2.1
Name: dfb
Version: 20250711.0b0
Summary: Dated File Backup
Home-page: https://github.com/Jwink3101/dfb/
Author: Justin Winokur
Author-email: Jwink3101@users.noreply.github.com
License: MIT
Requires-Python: >=3.9
Requires-Dist: requests
